basyx/__init__.py
basyx/py.typed
basyx/version.py
basyx/aas/__init__.py
basyx/aas/adapter/__init__.py
basyx/aas/adapter/_generic.py
basyx/aas/adapter/aasx.py
basyx/aas/adapter/json/__init__.py
basyx/aas/adapter/json/json_deserialization.py
basyx/aas/adapter/json/json_serialization.py
basyx/aas/adapter/xml/__init__.py
basyx/aas/adapter/xml/xml_deserialization.py
basyx/aas/adapter/xml/xml_serialization.py
basyx/aas/backend/__init__.py
basyx/aas/backend/couchdb.py
basyx/aas/backend/local_file.py
basyx/aas/examples/__init__.py
basyx/aas/examples/tutorial_aasx.py
basyx/aas/examples/tutorial_backend_couchdb.py
basyx/aas/examples/tutorial_create_simple_aas.py
basyx/aas/examples/tutorial_serialization_deserialization.py
basyx/aas/examples/tutorial_storage.py
basyx/aas/examples/data/TestFile.pdf
basyx/aas/examples/data/__init__.py
basyx/aas/examples/data/_helper.py
basyx/aas/examples/data/example_aas.py
basyx/aas/examples/data/example_aas_mandatory_attributes.py
basyx/aas/examples/data/example_aas_missing_attributes.py
basyx/aas/examples/data/example_submodel_template.py
basyx/aas/model/__init__.py
basyx/aas/model/_string_constraints.py
basyx/aas/model/aas.py
basyx/aas/model/base.py
basyx/aas/model/concept.py
basyx/aas/model/datatypes.py
basyx/aas/model/provider.py
basyx/aas/model/submodel.py
basyx/aas/util/__init__.py
basyx/aas/util/identification.py
basyx/aas/util/traversal.py
basyx_python_sdk-2.0.0.dist-info/METADATA
basyx_python_sdk-2.0.0.dist-info/WHEEL
basyx_python_sdk-2.0.0.dist-info/top_level.txt
basyx_python_sdk-2.0.0.dist-info/RECORD
