Metadata-Version: 2.4
Name: basyx-python-sdk
Version: 2.0.0
Summary: The Eclipse BaSyx Python SDK, an implementation of the Asset Administration Shell for Industry 4.0 systems
Author-email: The Eclipse BaSyx Authors <admins@iat.rwth-aachen.de>
Project-URL: Homepage, https://github.com/eclipse-basyx/basyx-python-sdk
Classifier: Programming Language :: Python :: 3
Classifier: License :: OSI Approved :: MIT License
Classifier: Operating System :: OS Independent
Classifier: Development Status :: 5 - Production/Stable
Requires-Python: >=3.10
Requires-Dist: lxml>=6.0.2
Requires-Dist: python-dateutil<3,>=2.8
Requires-Dist: pyecma376-2>=1.0.2
Provides-Extra: dev
Requires-Dist: mypy==1.15.0; extra == "dev"
Requires-Dist: pycodestyle; extra == "dev"
Requires-Dist: codeblocks; extra == "dev"
Requires-Dist: coverage; extra == "dev"
Requires-Dist: schemathesis~=3.7; extra == "dev"
Requires-Dist: jsonschema~=4.7; extra == "dev"
Requires-Dist: hypothesis~=6.13; extra == "dev"
Requires-Dist: types-python-dateutil; extra == "dev"
Requires-Dist: lxml-stubs~=0.5.1; extra == "dev"
Provides-Extra: docs
Requires-Dist: sphinx~=8.2; extra == "docs"
Requires-Dist: sphinx-rtd-theme~=3.0; extra == "docs"
Requires-Dist: sphinx-argparse~=0.5.0; extra == "docs"
